CHANGES.txt
MANIFEST.in
README.md
setup.cfg
setup.py
por/__init__.py
por.models.egg-info/PKG-INFO
por.models.egg-info/SOURCES.txt
por.models.egg-info/dependency_links.txt
por.models.egg-info/entry_points.txt
por.models.egg-info/namespace_packages.txt
por.models.egg-info/not-zip-safe
por.models.egg-info/requires.txt
por.models.egg-info/top_level.txt
por/models/__init__.py
por/models/dashboard.py
por/models/dbsession.py
por/models/dublincore.py
por/models/interfaces.py
por/models/tickets.py
por/models/tp.py
por/models/workflow.py
por/models/scripts/__init__.py
por/models/scripts/contracts_import.py
por/models/scripts/dummies.py
por/models/scripts/importsvn.py
por/models/scripts/populate.py
por/models/scripts/quality_export.py
por/models/tests/__init__.py
por/models/tests/test_dashboard.py
por/models/tests/test_tp.py