Metadata-Version: 1.0
Name: por.models
Version: 1.3.19
Summary: SQLAlchemy models for Penelope
Home-page: http://getpenelope.github.com
Author: Penelope Team
Author-email: penelopedev@redturtle.it
License: UNKNOWN
Keywords: web wsgi bfg pylons pyramid
Platform: UNKNOWN
Classifier: Programming Language :: Python
Classifier: Framework :: Pylons
Classifier: Topic :: Internet :: WWW/HTTP
Classifier: Topic :: Internet :: WWW/HTTP :: WSGI :: Application
